llama_index/vector_stores/redis/__init__.py
llama_index/vector_stores/redis/base.py
flying_delta_vector_stores_redis-0.1.1.dist-info/METADATA
flying_delta_vector_stores_redis-0.1.1.dist-info/WHEEL
flying_delta_vector_stores_redis-0.1.1.dist-info/RECORD
